odoo/addons/shopinvader_fastapi_auth_partner/README.rst
odoo/addons/shopinvader_fastapi_auth_partner/__init__.py
odoo/addons/shopinvader_fastapi_auth_partner/__manifest__.py
odoo/addons/shopinvader_fastapi_auth_partner/dependencies.py
odoo/addons/shopinvader_fastapi_auth_partner/helper.py
odoo/addons/shopinvader_fastapi_auth_partner/i18n/shopinvader_fastapi_auth_partner.pot
odoo/addons/shopinvader_fastapi_auth_partner/readme/DESCRIPTION.rst
odoo/addons/shopinvader_fastapi_auth_partner/readme/USAGE.rst
odoo/addons/shopinvader_fastapi_auth_partner/tests/__init__.py
odoo/addons/shopinvader_fastapi_auth_partner/tests/test_auth_partner_or_anonymous.py
odoo_addon_shopinvader_fastapi_auth_partner-16.0.1.0.0.5.dist-info/METADATA
odoo_addon_shopinvader_fastapi_auth_partner-16.0.1.0.0.5.dist-info/WHEEL
odoo_addon_shopinvader_fastapi_auth_partner-16.0.1.0.0.5.dist-info/top_level.txt
odoo_addon_shopinvader_fastapi_auth_partner-16.0.1.0.0.5.dist-info/RECORD
