Metadata-Version: 2.1
Name: odoo-addon-shopinvader_fastapi_auth_partner
Version: 16.0.1.0.0.5
Summary: Provide Partner and Anonymous Partner authentication to FastAPI routes.
Home-page: https://github.com/shopinvader/odoo-shopinvader
Author: Akretion
License: AGPL-3
Classifier: Programming Language :: Python
Classifier: Framework :: Odoo
Classifier: Framework :: Odoo :: 16.0
Classifier: License :: OSI Approved :: GNU Affero General Public License v3
Requires-Python: >=3.10
Requires-Dist: odoo-addon-fastapi-auth-partner<16.1dev,>=16.0dev
Requires-Dist: odoo-addon-shopinvader-anonymous-partner<16.1dev,>=16.0dev
Requires-Dist: odoo<16.1dev,>=16.0a
